flask_melodramatiq/__init__.py
flask_melodramatiq/lazy_broker.py
Flask_Melodramatiq-1.0.1.dist-info/LICENSE
Flask_Melodramatiq-1.0.1.dist-info/METADATA
Flask_Melodramatiq-1.0.1.dist-info/WHEEL
Flask_Melodramatiq-1.0.1.dist-info/top_level.txt
Flask_Melodramatiq-1.0.1.dist-info/zip-safe
Flask_Melodramatiq-1.0.1.dist-info/RECORD
