Metadata-Version: 2.1
Name: Flask-Melodramatiq
Version: 1.0.1
Summary: A Flask extension that adds support for the "dramatiq" task processing library
Home-page: https://github.com/epandurski/flask_melodramatiq
Author: Evgeni Pandurski
Author-email: epandurski@gmail.com
License: MIT
Project-URL: Bug Tracker, https://github.com/epandurski/flask_melodramatiq/issues
Project-URL: Documentation, https://flask-melodramatiq.readthedocs.io/en/latest/
Project-URL: Source Code, https://github.com/epandurski/flask_melodramatiq
Platform: any
Classifier: Environment :: Web Environment
Classifier: Intended Audience :: Developers
Classifier: License :: OSI Approved :: BSD License
Classifier: Operating System :: OS Independent
Classifier: Topic :: Internet :: WWW/HTTP :: Dynamic Content
Classifier: Topic :: Software Development :: Libraries :: Python Modules
Classifier: Programming Language :: Python
Classifier: Programming Language :: Python :: 3
Classifier: Programming Language :: Python :: 3.7
Classifier: Programming Language :: Python :: 3.8
Classifier: Programming Language :: Python :: 3.9
Classifier: Programming Language :: Python :: 3.10
License-File: LICENSE
Requires-Dist: Flask >=1.0
Requires-Dist: dramatiq >=1.5
